__init__.py
cus_config/__init__.py
cus_excel/__init__.py
cus_excel/cus_excel.py
cus_file/__init__.py
cus_file/cus_file.py
cus_log/__init__.py
cus_log/cus_log.py
cus_path/__init__.py
cus_path/cus_path.py
cus_pyside2/__init__.py
cus_pyside2/cus_pyside2.py
cus_subprocess/__init__.py
cus_subprocess/cus_subprocess.py
cus_lib-0.0.2.dist-info/METADATA
cus_lib-0.0.2.dist-info/WHEEL
cus_lib-0.0.2.dist-info/top_level.txt
cus_lib-0.0.2.dist-info/RECORD
