Metadata-Version: 2.1
Name: cus_lib
Version: 0.0.2
Summary: custom common fun
Author-email: lhy <oceanliu335372871@gmail.com>
Project-URL: Homepage, https://github.com/crazyetiii/common_lib
Project-URL: Issues, https://github.com/crazyetiii/common_lib/issues
Classifier: Programming Language :: Python :: 3
Classifier: License :: OSI Approved :: MIT License
Classifier: Operating System :: OS Independent
Requires-Python: >=3.8
